docker_slsa/__init__.py
docker_slsa/errors.py
docker_slsa/slsa.py
docker_slsa/utils.py
docker_slsa/verifier.py
docker_slsa-0.1.0.dist-info/licenses/LICENSE
docker_slsa-0.1.0.dist-info/WHEEL
docker_slsa-0.1.0.dist-info/METADATA
docker_slsa-0.1.0.dist-info/RECORD
