Metadata-Version: 2.4
Name: docker-slsa
Version: 0.1.0
Summary: Verify SLSA provenance attestations for Docker container images
Keywords: slsa,provenance,sigstore,docker,container,docker-compose,attestation,supply-chain,security
License-Expression: MIT
License-File: LICENSE
Classifier: Operating System :: OS Independent
Classifier: Programming Language :: Python :: 3
Classifier: Topic :: Security
Requires-Dist: oras>=0.2.38
Requires-Dist: pyyaml>=6.0
Requires-Dist: sigstore>=4.1.0
Requires-Python: >=3.10
Project-URL: Issues, https://github.com/concrete-security/docker-slsa/issues
Project-URL: Repository, https://github.com/concrete-security/docker-slsa.git
